{
    "name" : "Artificer-Repository",
    "jndiName" : "",
    "workspaces" : {
        "predefined" : ["otherWorkspace"],
        "default" : "default",
        "allowCreation" : false
    },
    "security" : {
        "anonymous" : {
            "useOnFailedLogin" : false
        },
        "providers" : [
            {
                "classname" : "JAAS",
                "policyName" : "overlord-idp"
            }
        ]
    },
    "storage" : {
        "cacheConfiguration" : "${modeshape.cache.config.url}",
        "cacheName" : "persisted-repository",
        "binaryStorage" : {
            "type" : "file",
            "directory": "${modeshape.jcr.datadir}/binary",
            "minimumBinarySizeInBytes" : 999
        }
    },
    "query" : {
        "indexStorage" : {
            "type" : "filesystem",
            "location" : "${modeshape.jcr.datadir}/index",
            "lockingStrategy" : "simple",
            "fileSystemAccessType" : "auto"
        }
    }
    

}